rankit/__init__.py
pyrankit-0.0.2.dist-info/LICENSE
pyrankit-0.0.2.dist-info/METADATA
pyrankit-0.0.2.dist-info/WHEEL
pyrankit-0.0.2.dist-info/top_level.txt
pyrankit-0.0.2.dist-info/RECORD
